nbdev_template/__init__.py
nbdev_template/_nbdev.py
nbdev_template/core.py
nbdev_guilhermemt21-0.0.1.dist-info/LICENSE
nbdev_guilhermemt21-0.0.1.dist-info/METADATA
nbdev_guilhermemt21-0.0.1.dist-info/WHEEL
nbdev_guilhermemt21-0.0.1.dist-info/entry_points.txt
nbdev_guilhermemt21-0.0.1.dist-info/top_level.txt
nbdev_guilhermemt21-0.0.1.dist-info/RECORD
